[
  {
    "code_raw": "SN 544",
    "code_norm": "SN 544",
    "family": "SN",
    "title": "Schlauchleitung SN 544 - NB 40 x 800",
    "subject_anchor": {
      "anchor_type": "section",
      "anchor_id": "3 Maße und Bezeichnungsbeispiele (Form NE, NF und NG siehe Seite 2)",
      "display_name": "3 Maße und Bezeichnungsbeispiele (Form NE, NF und NG siehe Seite 2)"
    },
    "source_refs": [
      {
        "page_index": 0,
        "block_id": "",
        "table_id": "",
        "row_index": -1,
        "col_index": -1,
        "node_id": "",
        "excerpt": "Schlauchleitung SN 544 - NB 40 x 800"
      }
    ]
  },
  {
    "code_raw": "SN 756",
    "code_norm": "SN 756",
    "family": "SN",
    "title": "Für Niederdruck-Schlauchleitungen bis DN 16 sind Schlauchleitungen nach SN 756 zu verwenden.",
    "subject_anchor": {
      "anchor_type": "section",
      "anchor_id": "U4 Form NF",
      "display_name": "U4 Form NF"
    },
    "source_refs": [
      {
        "page_index": 0,
        "block_id": "",
        "table_id": "",
        "row_index": -1,
        "col_index": -1,
        "node_id": "",
        "excerpt": "Für Niederdruck-Schlauchleitungen bis DN 16 sind Schlauchleitungen nach SN 756 zu verwenden."
      }
    ]
  },
  {
    "code_raw": "SN 544",
    "code_norm": "SN 544",
    "family": "SN",
    "title": "Doppelnippel, Anschweißnippel und Anwendungsbeispiel siehe SN 544 Teil 4.",
    "subject_anchor": {
      "anchor_type": "section",
      "anchor_id": "U4 Form NF",
      "display_name": "U4 Form NF"
    },
    "source_refs": [
      {
        "page_index": 0,
        "block_id": "",
        "table_id": "",
        "row_index": -1,
        "col_index": -1,
        "node_id": "",
        "excerpt": "Doppelnippel, Anschweißnippel und Anwendungsbeispiel siehe SN 544 Teil 4."
      }
    ]
  },
  {
    "code_raw": "SN 544",
    "code_norm": "SN 544",
    "family": "SN",
    "title": "Schlauchleitung SN 544 - NE 50 x 1000 St",
    "subject_anchor": {
      "anchor_type": "section",
      "anchor_id": "U5 Form NG",
      "display_name": "U5 Form NG"
    },
    "source_refs": [
      {
        "page_index": 0,
        "block_id": "",
        "table_id": "",
        "row_index": -1,
        "col_index": -1,
        "node_id": "",
        "excerpt": "Schlauchleitung SN 544 - NE 50 x 1000 St"
      }
    ]
  },
  {
    "code_raw": "SN 532",
    "code_norm": "SN 532",
    "family": "SN",
    "title": "separat in der Stückliste aufgegeben werden (siehe SN 532).",
    "subject_anchor": {
      "anchor_type": "section",
      "anchor_id": "U5 Form NG",
      "display_name": "U5 Form NG"
    },
    "source_refs": [
      {
        "page_index": 0,
        "block_id": "",
        "table_id": "",
        "row_index": -1,
        "col_index": -1,
        "node_id": "",
        "excerpt": "separat in der Stückliste aufgegeben werden (siehe SN 532)."
      }
    ]
  },
  {
    "code_raw": "SN 544",
    "code_norm": "SN 544",
    "family": "SN",
    "title": "Schlauchleitung SN 544 – NFG 32 x 800 – 140° gedreht",
    "subject_anchor": {
      "anchor_type": "section",
      "anchor_id": "5 Besondere Bezeichnungen",
      "display_name": "5 Besondere Bezeichnungen"
    },
    "source_refs": [
      {
        "page_index": 0,
        "block_id": "",
        "table_id": "",
        "row_index": -1,
        "col_index": -1,
        "node_id": "",
        "excerpt": "Schlauchleitung SN 544 – NFG 32 x 800 – 140° gedreht"
      }
    ]
  },
  {
    "code_raw": "SN 544-2",
    "code_norm": "SN 544-2",
    "family": "SN",
    "title": "SN 544-2 Niederdruck - Schlauchleitungen; Schläuche",
    "subject_anchor": {
      "anchor_type": "section",
      "anchor_id": "U6 Zitierte Normen",
      "display_name": "U6 Zitierte Normen"
    },
    "source_refs": [
      {
        "page_index": 0,
        "block_id": "",
        "table_id": "",
        "row_index": -1,
        "col_index": -1,
        "node_id": "",
        "excerpt": "SN 544-2 Niederdruck - Schlauchleitungen; Schläuche"
      }
    ]
  },
  {
    "code_raw": "SN 532-2",
    "code_norm": "SN 532-2",
    "family": "SN",
    "title": "5) SAE-Flansche siehe SN 532-2.",
    "subject_anchor": {
      "anchor_type": "section",
      "anchor_id": "U6 Zitierte Normen",
      "display_name": "U6 Zitierte Normen"
    },
    "source_refs": [
      {
        "page_index": 0,
        "block_id": "",
        "table_id": "",
        "row_index": -1,
        "col_index": -1,
        "node_id": "",
        "excerpt": "5) SAE-Flansche siehe SN 532-2."
      }
    ]
  },
  {
    "code_raw": "SN 544",
    "code_norm": "SN 544",
    "family": "SN",
    "title": "Schlauchleitung SN 544 - NB 40 x 800",
    "subject_anchor": {
      "anchor_type": "section",
      "anchor_id": "U2 Maße in mm",
      "display_name": "U2 Maße in mm"
    },
    "source_refs": [
      {
        "page_index": 0,
        "block_id": "",
        "table_id": "",
        "row_index": -1,
        "col_index": -1,
        "node_id": "",
        "excerpt": "Schlauchleitung SN 544 - NB 40 x 800"
      }
    ]
  },
  {
    "code_raw": "SN 756",
    "code_norm": "SN 756",
    "family": "SN",
    "title": "Für Niederdruck-Schlauchleitungen bis DN 16 sind Schlauchleitungen nach SN 756 zu verwenden.",
    "subject_anchor": {
      "anchor_type": "section",
      "anchor_id": "U2 Maße in mm",
      "display_name": "U2 Maße in mm"
    },
    "source_refs": [
      {
        "page_index": 0,
        "block_id": "",
        "table_id": "",
        "row_index": -1,
        "col_index": -1,
        "node_id": "",
        "excerpt": "Für Niederdruck-Schlauchleitungen bis DN 16 sind Schlauchleitungen nach SN 756 zu verwenden."
      }
    ]
  },
  {
    "code_raw": "SN 532",
    "code_norm": "SN 532",
    "family": "SN",
    "title": "separat in der Stückliste aufgegeben werden (siehe SN 532).",
    "subject_anchor": {
      "anchor_type": "section",
      "anchor_id": "U4 Form NF",
      "display_name": "U4 Form NF"
    },
    "source_refs": [
      {
        "page_index": 0,
        "block_id": "",
        "table_id": "",
        "row_index": -1,
        "col_index": -1,
        "node_id": "",
        "excerpt": "separat in der Stückliste aufgegeben werden (siehe SN 532)."
      }
    ]
  },
  {
    "code_raw": "SN 544",
    "code_norm": "SN 544",
    "family": "SN",
    "title": "Schlauchleitung SN 544 – NFG 32 x 800 – 140° gedreht",
    "subject_anchor": {
      "anchor_type": "section",
      "anchor_id": "4 Übersicht der Kombinationen von Schlaucharmaturen",
      "display_name": "4 Übersicht der Kombinationen von Schlaucharmaturen"
    },
    "source_refs": [
      {
        "page_index": 0,
        "block_id": "",
        "table_id": "",
        "row_index": -1,
        "col_index": -1,
        "node_id": "",
        "excerpt": "Schlauchleitung SN 544 – NFG 32 x 800 – 140° gedreht"
      }
    ]
  },
  {
    "code_raw": "SN 544-2",
    "code_norm": "SN 544-2",
    "family": "SN",
    "title": "SN 544-2 Niederdruck - Schlauchleitungen; Schläuche",
    "subject_anchor": {
      "anchor_type": "section",
      "anchor_id": "U2 Maße in mm",
      "display_name": "U2 Maße in mm"
    },
    "source_refs": [
      {
        "page_index": 0,
        "block_id": "",
        "table_id": "",
        "row_index": -1,
        "col_index": -1,
        "node_id": "",
        "excerpt": "SN 544-2 Niederdruck - Schlauchleitungen; Schläuche"
      }
    ]
  },
  {
    "code_raw": "SN 532-2",
    "code_norm": "SN 532-2",
    "family": "SN",
    "title": "5) SAE-Flansche siehe SN 532-2.",
    "subject_anchor": {
      "anchor_type": "section",
      "anchor_id": "U2 Maße in mm",
      "display_name": "U2 Maße in mm"
    },
    "source_refs": [
      {
        "page_index": 0,
        "block_id": "",
        "table_id": "",
        "row_index": -1,
        "col_index": -1,
        "node_id": "",
        "excerpt": "5) SAE-Flansche siehe SN 532-2."
      }
    ]
  }
]